aligned_textgrid/__init__.py
aligned_textgrid/aligned_textgrid.py
aligned_textgrid/custom_classes.py
aligned_textgrid/mixins/__init__.py
aligned_textgrid/mixins/mixins.py
aligned_textgrid/mixins/tiermixins.py
aligned_textgrid/mixins/within.py
aligned_textgrid/outputs/__init__.py
aligned_textgrid/outputs/to_dataframe.py
aligned_textgrid/points/__init__.py
aligned_textgrid/points/points.py
aligned_textgrid/points/tiers.py
aligned_textgrid/polar/__init__.py
aligned_textgrid/polar/polar_classes.py
aligned_textgrid/polar/polar_grid.py
aligned_textgrid/sequence_list.py
aligned_textgrid/sequences/__init__.py
aligned_textgrid/sequences/sequences.py
aligned_textgrid/sequences/tiers.py
aligned_textgrid/sequences/word_and_phone.py
aligned_textgrid-0.8.1.dist-info/LICENSE
aligned_textgrid-0.8.1.dist-info/METADATA
aligned_textgrid-0.8.1.dist-info/WHEEL
aligned_textgrid-0.8.1.dist-info/RECORD
