Metadata-Version: 2.3
Name: aligned_textgrid
Version: 0.8.1
Summary: Classes for defining sequential information from TextGrids
License: GPL-3.0-or-later
Author: JoFrhwld
Author-email: JoFrhwld@gmail.com
Requires-Python: >=3.10,<4.0
Classifier: License :: OSI Approved :: GNU General Public License v3 or later (GPLv3+)
Classifier: Programming Language :: Python :: 3
Classifier: Programming Language :: Python :: 3.10
Classifier: Programming Language :: Python :: 3.11
Classifier: Programming Language :: Python :: 3.12
Classifier: Programming Language :: Python :: 3.13
Requires-Dist: cloudpickle (>=3.0.0,<4.0.0)
Requires-Dist: numpy (>=2.1.0,<3.0.0)
Requires-Dist: polars (>=1.23.0,<2.0.0)
Requires-Dist: praatio (>=6.0.0,<7.0.0)
Requires-Dist: toml (>=0.10.2,<0.11.0)
Project-URL: Homepage, https://forced-alignment-and-vowel-extraction.github.io/alignedTextGrid/
Project-URL: Repository, https://github.com/Forced-Alignment-and-Vowel-Extraction/alignedTextGrid
